paystack/__init__.py
paystack/apple_pay.py
paystack/base.py
paystack/bulkcharge.py
paystack/charge.py
paystack/control_panel.py
paystack/customers.py
paystack/dedicated_virtual_accounts.py
paystack/disputes.py
paystack/invoices.py
paystack/misc.py
paystack/page.py
paystack/paystack.py
paystack/plans.py
paystack/products.py
paystack/refund.py
paystack/settlements.py
paystack/subaccounts.py
paystack/subscriptions.py
paystack/transaction_splits.py
paystack/transactions.py
paystack/transfer_control.py
paystack/transfer_recipient.py
paystack/transfers.py
paystack/verification.py
aiopaystack-2.0.0.dist-info/LICENSE
aiopaystack-2.0.0.dist-info/METADATA
aiopaystack-2.0.0.dist-info/WHEEL
aiopaystack-2.0.0.dist-info/top_level.txt
aiopaystack-2.0.0.dist-info/RECORD
