Metadata-Version: 2.1
Name: aiopaystack
Version: 2.0.0
Summary: Asynchronous PayStack library
Author-email: Ichinga Samuel <ichingasamuel@gmail.com>
Project-URL: Homepage, https://github.com/Ichinga-Samuel/aiopaystack
Project-URL: Bug Tracker, https://github.com/Ichinga-Samuel/aiopaystack/issues
Keywords: paystack,asynchronous
Classifier: Programming Language :: Python :: 3
Classifier: License :: OSI Approved :: MIT License
Classifier: Operating System :: OS Independent
Requires-Python: >=3.10
License-File: LICENSE
